{
  "type": "forge:conditional",
  "recipes": [
    {
      "conditions": [
        {
          "type": "forge:tag_empty",
          "tag": "forge:bread_slices"
        }
      ],
      "recipe": {
        "type": "minecraft:crafting_shapeless",
        "category": "misc",
        "ingredients": [
          {
            "tag": "forge:bread"
          },
          {
            "tag": "miners_delight:cooked_insect_meat"
          },
          {
            "tag": "miners_delight:cooked_insect_meat"
          }
        ],
        "result": {
          "item": "miners_delight:insect_sandwich"
        }
      }
    }
  ]
}