{
  "advancements": [
    {
      "conditions": [
        {
          "values": [
            {
              "value": "cooked_venison_chops",
              "type": "delightful:enabled"
            },
            {
              "value": "venison_chops",
              "type": "delightful:enabled"
            },
            {
              "value": {
                "tag": "forge:raw_venison",
                "type": "forge:tag_empty"
              },
              "type": "forge:not"
            }
          ],
          "type": "forge:and"
        }
      ],
      "advancement": {
        "parent": "minecraft:recipes/root",
        "rewards": {
          "recipes": [
            "delightful:smoking/venison_chops"
          ]
        },
        "criteria": {
          "has_venison_chops": {
            "trigger": "minecraft:inventory_changed",
            "conditions": {
              "items": [
                {
                  "items": [
                    "delightful:venison_chops"
                  ]
                }
              ]
            }
          },
          "has_the_recipe": {
            "trigger": "minecraft:recipe_unlocked",
            "conditions": {
              "recipe": "delightful:smoking/venison_chops"
            }
          }
        },
        "requirements": [
          [
            "has_venison_chops",
            "has_the_recipe"
          ]
        ]
      }
    }
  ]
}