{
  "type": "minecraft:crafting_shapeless",
  "ingredients": [
    {
      "item": "minecraft:dirt"
    },
    {
      "item": "farmersdelight:straw"
    },
    {
      "item": "farmersdelight:straw"
    },
    {
      "item": "minecraft:bone_meal"
    },
    {
      "item": "minecraft:bone_meal"
    },
    {
      "tag": "forge:bark"
    },
    {
      "tag": "forge:bark"
    },
    {
      "tag": "forge:bark"
    },
    {
      "tag": "forge:bark"
    }
  ],
  "result": {
    "item": "farmersdelight:organic_compost"
  }
}