{
  "type": "forge:conditional",
  "recipes": [
    {
      "conditions": [
        {
          "type": "forge:and",
          "values": [
            {
              "type": "delightful:enabled",
              "value": "nut_milk"
            },
            {
              "type": "forge:not",
              "value": {
                "type": "forge:mod_loaded",
                "modid": "vintagedelight"
              }
            }
          ]
        }
      ],
      "recipe": {
        "type": "farmersdelight:cooking",
        "container": {
          "item": "minecraft:bucket"
        },
        "cookingtime": 200,
        "experience": 0.35,
        "ingredients": [
          {
            "tag": "forge:water"
          },
          {
            "tag": "forge:nuts"
          },
          {
            "tag": "forge:nuts"
          },
          {
            "tag": "forge:sugar"
          }
        ],
        "result": {
          "item": "minecraft:milk_bucket"
        }
      }
    }
  ]
}